sgsuite/ClusterNews.py
sgsuite/__init__.py
sgsuite/rss_parser.py
sgsuite/util.py
sgsuite/version.py
sgsuite-0.0.0.data/scripts/sgs
sgsuite-0.0.0.dist-info/LICENSE
sgsuite-0.0.0.dist-info/METADATA
sgsuite-0.0.0.dist-info/WHEEL
sgsuite-0.0.0.dist-info/top_level.txt
sgsuite-0.0.0.dist-info/RECORD
