Metadata-Version: 2.1
Name: sgsuite
Version: 0.0.0
Summary: A collection of software used by StoryGraphs (http://storygraph.cs.odu.edu/)
Home-page: https://github.com/oduwsdl/storygraph-suite
Author: Alexander C. Nwala
Author-email: alexandernwala@gmail.com
License: MIT
Platform: UNKNOWN
Classifier: Programming Language :: Python :: 3
Classifier: License :: OSI Approved :: MIT License
Classifier: Operating System :: OS Independent
Requires-Dist: beautifulsoup4 (>=4.8)
Requires-Dist: boilerpy3
Requires-Dist: dateparser (>=0.7)
Requires-Dist: feedparser (>=5.2)
Requires-Dist: requests (>=2.20)
Requires-Dist: tldextract (>=2.2)
Requires-Dist: networkx (>=2.4)
Requires-Dist: NwalaTextUtils (==0.0.4)
Requires-Dist: spacy (>=3.1.0)
